README.md
setup.py
kismetexternal/__init__.py
kismetexternal/datasource_pb2.py
kismetexternal/eventbus_pb2.py
kismetexternal/http_pb2.py
kismetexternal/kismet_pb2.py
kismetexternal/linuxbluetooth_pb2.py
kismetexternal.egg-info/PKG-INFO
kismetexternal.egg-info/SOURCES.txt
kismetexternal.egg-info/dependency_links.txt
kismetexternal.egg-info/requires.txt
kismetexternal.egg-info/top_level.txt
kismetexternal/protobuf/__init__.py