Metadata-Version: 1.2
Name: kismetexternal
Version: 2020.7.1
Summary: Kismet External Helper Library
Home-page: https://www.kismetwireless.net/
Author: Mike Kershaw / Dragorn
Author-email: dragorn@kismetwireless.net
License: UNKNOWN
Platform: UNKNOWN
Requires-Python: >=3.2
